disjoint_forest/__init__.py
disjoint_forest/cli.py
disjoint_forest/disjoint_forest.cpython-310-x86_64-linux-gnu.so
disjoint_forest-1.1.dist-info/METADATA
disjoint_forest-1.1.dist-info/WHEEL
disjoint_forest-1.1.dist-info/top_level.txt
disjoint_forest-1.1.dist-info/RECORD
